CMakeLists.txt
LICENSE
MANIFEST.in
README.md
setup.cfg
setup.py
lib/pybind11_mod/CMakeLists.txt
lib/pybind11_mod/include/pybind11/attr.h
lib/pybind11_mod/include/pybind11/buffer_info.h
lib/pybind11_mod/include/pybind11/cast.h
lib/pybind11_mod/include/pybind11/chrono.h
lib/pybind11_mod/include/pybind11/common.h
lib/pybind11_mod/include/pybind11/complex.h
lib/pybind11_mod/include/pybind11/eigen.h
lib/pybind11_mod/include/pybind11/embed.h
lib/pybind11_mod/include/pybind11/eval.h
lib/pybind11_mod/include/pybind11/functional.h
lib/pybind11_mod/include/pybind11/gil.h
lib/pybind11_mod/include/pybind11/iostream.h
lib/pybind11_mod/include/pybind11/numpy.h
lib/pybind11_mod/include/pybind11/operators.h
lib/pybind11_mod/include/pybind11/options.h
lib/pybind11_mod/include/pybind11/pybind11.h
lib/pybind11_mod/include/pybind11/pytypes.h
lib/pybind11_mod/include/pybind11/stl.h
lib/pybind11_mod/include/pybind11/stl_bind.h
lib/pybind11_mod/include/pybind11/detail/class.h
lib/pybind11_mod/include/pybind11/detail/common.h
lib/pybind11_mod/include/pybind11/detail/descr.h
lib/pybind11_mod/include/pybind11/detail/init.h
lib/pybind11_mod/include/pybind11/detail/internals.h
lib/pybind11_mod/include/pybind11/detail/type_caster_base.h
lib/pybind11_mod/include/pybind11/detail/typeid.h
lib/pybind11_mod/include/pybind11/stl/filesystem.h
lib/pybind11_mod/pybind11/__init__.py
lib/pybind11_mod/pybind11/__main__.py
lib/pybind11_mod/pybind11/_version.py
lib/pybind11_mod/pybind11/commands.py
lib/pybind11_mod/pybind11/py.typed
lib/pybind11_mod/pybind11/setup_helpers.py
lib/pybind11_mod/tools/FindCatch.cmake
lib/pybind11_mod/tools/FindEigen3.cmake
lib/pybind11_mod/tools/FindPythonLibsNew.cmake
lib/pybind11_mod/tools/check-style.sh
lib/pybind11_mod/tools/cmake_uninstall.cmake.in
lib/pybind11_mod/tools/libsize.py
lib/pybind11_mod/tools/make_changelog.py
lib/pybind11_mod/tools/pybind11Common.cmake
lib/pybind11_mod/tools/pybind11Config.cmake.in
lib/pybind11_mod/tools/pybind11NewTools.cmake
src/python_cpp_example_peresec.egg-info/PKG-INFO
src/python_cpp_example_peresec.egg-info/SOURCES.txt
src/python_cpp_example_peresec.egg-info/dependency_links.txt
src/python_cpp_example_peresec.egg-info/not-zip-safe
src/python_cpp_example_peresec.egg-info/top_level.txt