Metadata-Version: 2.1
Name: python-cpp-example-peresec
Version: 0.0.8
Summary: Testing a custom extension module
Home-page: https://github.com/jamescalam/aesthetic_ascii
Author: Scrot Scratch
Author-email: scratch@gmail.com
Classifier: Programming Language :: Python :: 3
Classifier: License :: OSI Approved :: MIT License
Classifier: Operating System :: OS Independent
Requires-Python: >=3.7
License-File: LICENSE
